HDL/BCD_to_7_segment/BCD_to_7_segment.srcs/sources_1/new/BCD_to_7_segment.v
`timescale 1ns / 1ps
//////////////////////////////////////////////////////////////////////////////////
// Company: 
// Engineer: 
// 
// Create Date: 03/17/2025 12:57:13 PM
// Design Name: 
// Module Name: BCD_to_7_segment
// Project Name: 
// Target Devices: 
// Tool Versions: 
// Description: 
// 
// Dependencies: 
// 
// Revision:
// Revision 0.01 - File Created
// Additional Comments:
// 
//////////////////////////////////////////////////////////////////////////////////


module BCD_to_7_segment(
input [3:0] BCD,
output reg [6:0] segment,
output reg a,b,c,d,e,f,g
    );
always @(BCD) begin
    case(BCD)
        4'b0000: segment = 7'b1111110;
        4'b0001: segment = 7'b0110000;
        4'b0010: segment = 7'b1101101;
        4'b0011: segment = 7'b1111001;
        4'b0100: segment = 7'b0110011;
        4'b0101: segment = 7'b1011011;
        4'b0110: segment = 7'b1011111;
        4'b0111: segment = 7'b1110000;
        4'b1000: segment = 7'b1111111;
        4'b1001: segment = 7'b1111011;
        default: segment = 7'bx;
    endcase
    a = segment[6];
    b = segment[5];
    c = segment[4];
    d = segment[3];
    e = segment[2];
    f = segment[1];
    g = segment[0];
end

endmodule

HDL/BCD_to_7_segment/BCD_to_7_segment.srcs/sources_1/new/tb.v
`timescale 1ns / 1ps
//////////////////////////////////////////////////////////////////////////////////
// Company: 
// Engineer: 
// 
// Create Date: 03/17/2025 01:48:37 PM
// Design Name: 
// Module Name: tb
// Project Name: 
// Target Devices: 
// Tool Versions: 
// Description: 
// 
// Dependencies: 
// 
// Revision:
// Revision 0.01 - File Created
// Additional Comments:
// 
//////////////////////////////////////////////////////////////////////////////////


module tb;
reg [3:0] BCD;
wire [6:0] segment;
wire a,b,c,d,e,f,g;
BCD_to_7_segment dut(.BCD(BCD),.segment(segment),.a(a),.b(b),.c(c),.d(d),.e(e),.f(f),.g(g));
initial begin
    $dumpfile("tb.vcd");
    $dumpvars(0,tb);
    BCD = 4'b0000;
    #10 BCD = 4'b0001;
    #10 BCD = 4'b0010;
    #10 BCD = 4'b0011;
    #10 BCD = 4'b0100;
    #10 BCD = 4'b0101;
    #10 BCD = 4'b0110;
    #10 BCD = 4'b0111;
    #10 BCD = 4'b1000;
    #10 BCD = 4'b1001;
    #10 BCD = 4'b1010;
    #10 BCD = 4'b1011;
    #10 BCD = 4'b1100;
    #10 BCD = 4'b1101;
    #10 BCD = 4'b1110;
    #10 BCD = 4'b1111;
    #10 $finish;
end
endmodule

HDL/BCD_to_7_segment/BCD_to_7_segment.sim/sim_1/behav/xsim/tb.vcd
$date
   Mon Mar 17 15:03:52 2025
$end
$version
  2022.2
$end
$timescale
  1ps
$end
$scope module tb $end
$var reg 4 ! BCD [3:0] $end
$var wire 7 " segment [6:0] $end
$var wire 1 # a $end
$var wire 1 $ b $end
$var wire 1 % c $end
$var wire 1 & d $end
$var wire 1 ' e $end
$var wire 1 ( f $end
$var wire 1 ) g $end
$scope module dut $end
$var wire 4 * BCD [3:0] $end
$var reg 7 + segment [6:0] $end
$var reg 1 , a $end
$var reg 1 - b $end
$var reg 1 . c $end
$var reg 1 / d $end
$var reg 1 0 e $end
$var reg 1 1 f $end
$var reg 1 2 g $end
$upscope $end
$upscope $end
$enddefinitions $end
#0
$dumpvars
b0 !
b1111110 "
1#
1$
1%
1&
1'
1(
0)
b0 *
b1111110 +
1,
1-
1.
1/
10
11
02
$end
#10000
b1 !
b110000 "
0#
0&
0'
0(
b1 *
b110000 +
0,
1-
1.
0/
00
01
02
#20000
b10 !
b1101101 "
1#
0%
1&
1'
1)
b10 *
b1101101 +
1,
1-
0.
1/
10
01
12
#30000
b11 !
b1111001 "
1%
0'
b11 *
b1111001 +
1,
1-
1.
1/
00
01
12
#40000
b100 !
b110011 "
0#
0&
1(
b100 *
b110011 +
0,
1-
1.
0/
00
11
12
#50000
b101 !
b1011011 "
1#
0$
1&
b101 *
b1011011 +
1,
0-
1.
1/
00
11
12
#60000
b110 !
b1011111 "
1'
b110 *
b1011111 +
1,
0-
1.
1/
10
11
12
#70000
b111 !
b1110000 "
1$
0&
0'
0(
0)
b111 *
b1110000 +
1,
1-
1.
0/
00
01
02
#80000
b1000 !
b1111111 "
1&
1'
1(
1)
b1000 *
b1111111 +
1,
1-
1.
1/
10
11
12
#90000
b1001 !
b1111011 "
0'
b1001 *
b1111011 +
1,
1-
1.
1/
00
11
12
#100000
b1010 !
bx "
x#
x$
x%
x&
x'
x(
x)
b1010 *
bx +
x,
x-
x.
x/
x0
x1
x2
#110000
b1011 !
b1011 *
bx +
x,
x-
x.
x/
x0
x1
x2
#120000
b1100 !
b1100 *
bx +
x,
x-
x.
x/
x0
x1
x2
#130000
b1101 !
b1101 *
bx +
x,
x-
x.
x/
x0
x1
x2
#140000
b1110 !
b1110 *
bx +
x,
x-
x.
x/
x0
x1
x2
#150000
b1111 !
b1111 *
bx +
x,
x-
x.
x/
x0
x1
x2
